kypy/KyvosLib.py
kypy/__init__.py
kypy/Metadata/OlapQueriesLib.py
kypy/Metadata/__init__.py
kypy/Statistics/KyvosMLLib.py
kypy/Statistics/__init__.py
kypy-0.3.17.dist-info/LICENSE
kypy-0.3.17.dist-info/METADATA
kypy-0.3.17.dist-info/WHEEL
kypy-0.3.17.dist-info/top_level.txt
kypy-0.3.17.dist-info/RECORD
