Metadata-Version: 2.1
Name: kypy
Version: 0.3.17
Summary: A python client library used to encapsulating Kyvos OLAP cube patterns.
Home-page: https://github.com/eugenea-kyvos/KyPy.git
Author: Eugene Asahara
Author-email: eugene.asahara@kyvos.io
License: UNKNOWN
Keywords: kyvos insights,OLAP cubes,SmartOLAP
Platform: UNKNOWN
Classifier: Development Status :: 3 - Alpha
Classifier: Natural Language :: English
Classifier: Operating System :: OS Independent
Classifier: Programming Language :: Python
Classifier: Programming Language :: Python :: 3
Classifier: Programming Language :: Python :: 3.8
Classifier: Topic :: Database
Requires-Python: >=3.7
Requires-Dist: pyodbc
Requires-Dist: pandas
Requires-Dist: sklearn
Requires-Dist: matplotlib
Requires-Dist: seaborn
